MANIFEST.in
README.md
pyproject.toml
setup.py
docs/Makefile
docs/api.rst
docs/conf.py
docs/index.rst
docs/make.bat
src/PySimpleValidate.egg-info/PKG-INFO
src/PySimpleValidate.egg-info/SOURCES.txt
src/PySimpleValidate.egg-info/dependency_links.txt
src/PySimpleValidate.egg-info/requires.txt
src/PySimpleValidate.egg-info/top_level.txt
src/pysimplevalidate/__init__.py
src/pysimplevalidate/test1.py
tests/test_pysimplevalidate.py