Metadata-Version: 1.1
Name: PySimpleValidate
Version: 0.2.11
Summary: A collection of string-based validation functions, suitable for use in other Python 2 and 3 applications.
Home-page: https://github.com/asweigart/pysimplevalidate
Author: Al Sweigart
Author-email: al@inventwithpython.com
License: BSD
Keywords: input validation text string
Platform: UNKNOWN
Classifier: Development Status :: 4 - Beta
Classifier: Intended Audience :: Developers
Classifier: License :: OSI Approved :: BSD License
Classifier: Operating System :: OS Independent
Classifier: Programming Language :: Python
Classifier: Programming Language :: Python :: 2
Classifier: Programming Language :: Python :: 2.7
Classifier: Programming Language :: Python :: 3
Classifier: Programming Language :: Python :: 3.4
Classifier: Programming Language :: Python :: 3.5
Classifier: Programming Language :: Python :: 3.6
Classifier: Programming Language :: Python :: 3.7
Classifier: Programming Language :: Python :: 3.8
